[
  {
    "id": "case001",
    "title_of_original": "State Aid SA.38330 (2016/FC) – Poland Alleged unlawful regional investment aid to PCC MCAA sp. Zo.o (PCC)",
    "link_to_original": "https://ec.europa.eu/competition/state_aid/cases1/202016/282908_2148733_65_2.pdf",
    "decided_by": "European Commission",
    "type_of_measure": "Grant",
    "state_aid": "False",
    "selected_because": "simple general case"
  },
  {
    "id": "case002",
    "title_of_original": "State Aid SA.38330 (2016/FC) – Poland Alleged unlawful regional investment aid to PCC MCAA sp. Zo.o (PCC)",
    "link_to_original": "https://ec.europa.eu/competition/state_aid/cases1/202016/282908_2148733_65_2.pdf",    
    "decided_by": "European Commission",
    "type_of_measure": "Tax Exemption",
    "state_aid": "False",
    "selected_because": "simple general case"
  },
  {
    "id": "case003",
    "title_of_original": "State Aid SA.115160 (2024/NN) - Germany Measures concerning Haitec AG, Flughafen Frankfurt Hahn GmbH, and Ryanair",
    "link_to_original": "https://ec.europa.eu/competition/state_aid/cases1/202442/SA_115160_16.pdf",    
    "decided_by": "European Commission",
    "type_of_measure": "Option Fee",
    "state_aid": "False",
    "selected_because": "Reasoning over Market Economy Operator Test"
  },
  {
    "id": "case004",
    "title_of_original": "State Aid SA.115160 (2024/NN) - Germany Measures concerning Haitec AG, Flughafen Frankfurt Hahn GmbH, and Ryanair",
    "link_to_original": "https://ec.europa.eu/competition/state_aid/cases1/20255/SA_57025_363.pdf",    
    "decided_by": "European Commission",
    "type_of_measure": "Equity instruments",
    "state_aid": "True",
    "selected_because": "simple general case"
  }
{
    "id": "case004",
    "title_of_original": "State Aid SA.115160 (2024/NN) - Germany Measures concerning Haitec AG, Flughafen Frankfurt Hahn GmbH, and Ryanair",
    "link_to_original": "https://ec.europa.eu/competition/state_aid/cases1/20255/SA_57025_363.pdf",    
    "decided_by": "European Commission",
    "type_of_measure": "Equity instruments",
    "state_aid": "True",
    "selected_because": "Reasoning over Market Economy Operator"
  }
{
    "id": "case004",
    "title_of_original": "State Aid SA.115160 (2024/NN) - Germany Measures concerning Haitec AG, Flughafen Frankfurt Hahn GmbH, and Ryanair",
    "link_to_original": "https://ec.europa.eu/competition/state_aid/cases1/20255/SA_57025_363.pdf",    
    "decided_by": "European Commission",
    "type_of_measure": "Equity instruments",
    "state_aid": "True",
    "selected_because": "Reasoning over Market Economy Operator"
  }
]